db_drift/__init__.py
db_drift/__main__.py
db_drift/cli/__init__.py
db_drift/cli/cli.py
db_drift/cli/utils.py
db_drift/db/__init__.py
db_drift/db/factory.py
db_drift/db/connectors/__init__.py
db_drift/db/connectors/base_connector.py
db_drift/db/connectors/oracle.py
db_drift/db/connectors/sqlite.py
db_drift/db/strategies/__init__.py
db_drift/db/strategies/oracle.py
db_drift/models/__init__.py
db_drift/models/abstract_models.py
db_drift/models/column.py
db_drift/models/complex_abstract_models.py
db_drift/models/constraint.py
db_drift/models/directory.py
db_drift/models/function.py
db_drift/models/index.py
db_drift/models/materialized_view.py
db_drift/models/package.py
db_drift/models/sequence.py
db_drift/models/stored_procedures.py
db_drift/models/synonym.py
db_drift/models/table.py
db_drift/models/trigger.py
db_drift/models/type.py
db_drift/models/view.py
db_drift/report/__init__.py
db_drift/report/generate.py
db_drift/utils/__init__.py
db_drift/utils/constants.py
db_drift/utils/custom_logging.py
db_drift/utils/exceptions/__init__.py
db_drift/utils/exceptions/base.py
db_drift/utils/exceptions/cli.py
db_drift/utils/exceptions/config.py
db_drift/utils/exceptions/database.py
db_drift/utils/exceptions/formatting.py
db_drift-1.3.6.dist-info/METADATA
db_drift-1.3.6.dist-info/WHEEL
db_drift-1.3.6.dist-info/entry_points.txt
db_drift-1.3.6.dist-info/licenses/LICENSE
db_drift-1.3.6.dist-info/RECORD
