Metadata-Version: 2.4
Name: db-drift
Version: 1.3.6
Summary: A command line tool to visualize the differences between two DB states.
Project-URL: source, https://github.com/dyka3773/db-drift
Project-URL: documentation, https://dyka3773.github.io/db-drift/
Author-email: Hercules Konsoulas <dyka3773@gmail.com>
License-Expression: MIT
License-File: LICENSE
Keywords: cli,command-line,database,db-drift,diff,visualization
Classifier: Development Status :: 3 - Alpha
Classifier: Intended Audience :: Developers
Classifier: License :: OSI Approved :: MIT License
Classifier: Programming Language :: Python :: 3
Classifier: Programming Language :: Python :: 3.13
Classifier: Topic :: Database
Classifier: Topic :: Software Development :: Build Tools
Classifier: Topic :: Software Development :: Version Control
Classifier: Topic :: Utilities
Classifier: Typing :: Typed
Requires-Python: >=3.10
Requires-Dist: oracledb==3.4.1
Requires-Dist: psycopg[binary]==3.3.2
Requires-Dist: pymysql==1.1.2
Requires-Dist: python-dotenv==1.2.1
Requires-Dist: pyyaml==6.0.3
Requires-Dist: sqlmodel==0.0.31
Requires-Dist: sshtunnel==0.4.0
